reedsolomon/__init__.py
reedsolomon/galoisfield.py
reedsolomon/polynomial.py
reedsolomon/reedsolomon.py
reedsolomon/examples/__init__.py
reedsolomon-0.0.3.dist-info/licenses/LICENSE.md
reedsolomon-0.0.3.dist-info/METADATA
reedsolomon-0.0.3.dist-info/WHEEL
reedsolomon-0.0.3.dist-info/entry_points.txt
reedsolomon-0.0.3.dist-info/top_level.txt
reedsolomon-0.0.3.dist-info/RECORD
