Metadata-Version: 2.4
Name: reedsolomon
Version: 0.0.3
Summary: A Python package for Reed-Solomon error correction codes
Author-email: Archange <archange_paradise@proton.me>
License: MIT
Project-URL: Homepage, https://github.com/Archange-py/Reed-Solomon_Codes
Project-URL: Repository, https://github.com/Archange-py/Reed-Solomon_Codes
Project-URL: Library, https://pypi.org/project/reedsolomon/
Keywords: reedsolomon,POO,error-correcting code
Classifier: Programming Language :: Python :: 3
Classifier: License :: OSI Approved :: MIT License
Classifier: Operating System :: OS Independent
Requires-Python: >=3.12.4
License-File: LICENSE.md
Requires-Dist: mpmath==1.3.0
Requires-Dist: sympy==1.13.3
Provides-Extra: dev
Requires-Dist: pytest; extra == "dev"
Dynamic: license-file
